cube/__init__.py
cube/api.py
cube/trainer.py
cube/version.py
cube/webserver.py
cube/io_utils/__init__.py
cube/io_utils/components.py
cube/io_utils/config.py
cube/io_utils/encodings.py
cube/io_utils/misc.py
cube/io_utils/modelstore.py
cube/io_utils/objects.py
cube/misc/__init__.py
cube/misc/conll18_ud_eval.py
cube/misc/conll18_ud_eval_wrapper.py
cube/networks/__init__.py
cube/networks/compound.py
cube/networks/dcwe.py
cube/networks/lemmatizer.py
cube/networks/lm.py
cube/networks/modules.py
cube/networks/parser.py
cube/networks/tagger.py
cube/networks/tokenizer.py
cube/networks/utils.py
cube/networks/utils_dcwe.py
cube/networks/utils_tokenizer.py
scripts/__init__.py
scripts/_del_pack_models_for_upload.py
scripts/export_model.py
scripts/generate_catalog_from_models.py
scripts/generate_training_yamls.py
scripts/import_model.py
scripts/list2train.py
scripts/package_ud_models.py
scripts/reshape_unimorf.py
scripts/result_mdtable_generator.py
scripts/test_all_models.py
scripts/utils.py
nlpcube-0.3.1.2.dist-info/AUTHORS.md
nlpcube-0.3.1.2.dist-info/LICENSE
nlpcube-0.3.1.2.dist-info/METADATA
nlpcube-0.3.1.2.dist-info/WHEEL
nlpcube-0.3.1.2.dist-info/top_level.txt
nlpcube-0.3.1.2.dist-info/RECORD
