Metadata-Version: 2.1
Name: nlpcube
Version: 0.3.1.2
Summary: Natural Language Processing Toolkit with support for tokenization, sentence splitting, lemmatization, tagging and parsing for more than 60 languages
Home-page: https://github.com/adobe/NLP-Cube
Author: Multiple authors
Author-email: tiberiu44@gmail.com
Classifier: Programming Language :: Python :: 3.0
Classifier: License :: OSI Approved :: Apache Software License
Classifier: Operating System :: OS Independent
License-File: LICENSE
License-File: AUTHORS.md
Requires-Dist: beautifulsoup4 (==4.12.2)
Requires-Dist: fasttext (==0.9.2)
Requires-Dist: Flask (==2.3.2)
Requires-Dist: numpy (==1.25.0)
Requires-Dist: pytorch-lightning (==2.0.3)
Requires-Dist: PyYAML (==6.0)
Requires-Dist: Requests (==2.31.0)
Requires-Dist: setuptools (==67.7.2)
Requires-Dist: torch (==2.0.1)
Requires-Dist: tqdm (==4.65.0)
Requires-Dist: transformers (==4.30.2)
